{"OutputFileHashSum":"E43041F9BB9AE90226CFBAE2FED89580AC391E2BE6909231C024752664894CA1","Converted":true,"OutputModifyDate":"2019-11-28T11:48:15.0941467Z","Metadatas":[],"MetadataTypes":[{"CategoryName":"VuGen.Replay","MetadataTypeName":"HP.LR.Vugen.Iteration","Id":1},{"CategoryName":"VuGen.Replay","MetadataTypeName":"HP.LR.Vugen.NotifyTransaction","Id":2},{"CategoryName":"VuGen.Replay","MetadataTypeName":"Utt.Debugger.Error","Id":3},{"CategoryName":"VuGen.Replay","MetadataTypeName":"HP.LR.Vugen.NotifyAny","Id":4}]}