[
    {
        "actionName": "vuser_init",
        "steps": [
            {
                "stepId": "STEP1",
                "stepName": "Url: Homepage_2",
                "infFile": "t3.inf",
                "time": 1575469843472
            },
            {
                "stepId": "STEP2",
                "stepName": "Url: /api/checkLogin",
                "infFile": "t4.inf",
                "time": 1575469843551
            },
            {
                "stepId": "STEP3",
                "stepName": "Url: /api/user/info",
                "infFile": "t5.inf",
                "time": 1575469843638
            },
            {
                "stepId": "STEP4",
                "stepName": "Url: /api/ticket/countByState/4",
                "infFile": "t6.inf",
                "time": 1575469843739
            },
            {
                "stepId": "STEP5",
                "stepName": "Url: /api/ticket/countByState/",
                "infFile": "t7.inf",
                "time": 1575469843866
            },
            {
                "stepId": "STEP6",
                "stepName": "Custom Request: /api/ticket/?state=-1,0,1,5&page=0&size=10",
                "infFile": "t8.inf",
                "time": 1575469846765
            }
        ],
        "transactions": [
            {
                "transactionName": "UC1_TR1_LOGIN",
                "rawStartTime": 1575469842602,
                "rawEndTime": 1575469846767,
                "thinkTime": 0.0,
                "wastedTime": 0.3260033130645752
            }
        ]
    },
    {
        "actionName": "Create_task",
        "steps": [
            {
                "stepId": "STEP7",
                "stepName": "Url: /api/user/catalog/node/0/children/",
                "infFile": "t9.inf",
                "time": 1575469847085
            },
            {
                "stepId": "STEP8",
                "stepName": "Url: /api/shops?q=&page=0",
                "infFile": "t11.inf",
                "time": 1575469847294
            },
            {
                "stepId": "STEP9",
                "stepName": "Custom Request: DB_Request",
                "infFile": "t12.inf",
                "time": 1575469847444
            },
            {
                "stepId": "STEP10",
                "stepName": "Url: /api/user/catalog/node/0/children/",
                "infFile": "t13.inf",
                "time": 1575469847501
            },
            {
                "stepId": "STEP11",
                "stepName": "Url: /api/user/catalog/treeview?shopid={shopid}",
                "infFile": "t16.inf",
                "time": 1575469847955
            },
            {
                "stepId": "STEP12",
                "stepName": "Custom Request: DB_Request",
                "infFile": "t17.inf",
                "time": 1575469848019
            },
            {
                "stepId": "STEP13",
                "stepName": "Url: /api/user/catalog/node/191/children/",
                "infFile": "t18.inf",
                "time": 1575469848191
            },
            {
                "stepId": "STEP14",
                "stepName": "Url: /api/user/catalog/node/191/service/",
                "infFile": "t19.inf",
                "time": 1575469848277
            },
            {
                "stepId": "STEP15",
                "stepName": "Url: /api/user/catalog/breadcrumbs/191",
                "infFile": "t20.inf",
                "time": 1575469848366
            },
            {
                "stepId": "STEP16",
                "stepName": "Url: /api/inventoryNumbers?serviceId={serviceID}&shopId={shopid}",
                "infFile": "t22.inf",
                "time": 1575469848460
            },
            {
                "stepId": "STEP17",
                "stepName": "Custom Request: DB_Request",
                "infFile": "t23.inf",
                "time": 1575469848534
            },
            {
                "stepId": "STEP18",
                "stepName": "Url: /api/inventoryNumbers?shopId={shopid}&serviceId={serviceID}&serviceId={serviceID}&q=&page=0",
                "infFile": "t24.inf",
                "time": 1575469848747
            },
            {
                "stepId": "STEP19",
                "stepName": "Custom Request: /api/ticket/",
                "infFile": "t25.inf",
                "time": 1575469849483
            },
            {
                "stepId": "STEP20",
                "stepName": "Custom Request: DB_Request",
                "infFile": "t26.inf",
                "time": 1575469849535
            },
            {
                "stepId": "STEP21",
                "stepName": "Url: {URL}:{port}_3",
                "infFile": "t27.inf",
                "time": 1575469849684
            },
            {
                "stepId": "STEP22",
                "stepName": "Url: /api/checkLogin",
                "infFile": "t28.inf",
                "time": 1575469849771
            },
            {
                "stepId": "STEP23",
                "stepName": "Url: /api/user/info",
                "infFile": "t29.inf",
                "time": 1575469849856
            },
            {
                "stepId": "STEP24",
                "stepName": "Url: /api/ticket/countByState/4",
                "infFile": "t30.inf",
                "time": 1575469849938
            },
            {
                "stepId": "STEP25",
                "stepName": "Url: /api/ticket/countByState/",
                "infFile": "t31.inf",
                "time": 1575469850030
            }
        ],
        "transactions": [
            {
                "transactionName": "UC1_TR2_NEWINC",
                "rawStartTime": 1575469846954,
                "rawEndTime": 1575469847087,
                "thinkTime": 0.0,
                "wastedTime": 0.019188404083251954
            },
            {
                "transactionName": "UC1_TR3_LOCATION",
                "rawStartTime": 1575469847157,
                "rawEndTime": 1575469848022,
                "thinkTime": 0.0,
                "wastedTime": 0.1593334674835205
            },
            {
                "transactionName": "UC1_TR4_QUESTION",
                "rawStartTime": 1575469848110,
                "rawEndTime": 1575469848536,
                "thinkTime": 0.0,
                "wastedTime": 0.09179139137268067
            },
            {
                "transactionName": "UC1_TR5_INVNUMBER",
                "rawStartTime": 1575469848609,
                "rawEndTime": 1575469848749,
                "thinkTime": 0.0,
                "wastedTime": 0.018972396850585939
            },
            {
                "transactionName": "UC1_TR7_CREATE",
                "rawStartTime": 1575469848831,
                "rawEndTime": 1575469849537,
                "thinkTime": 0.0,
                "wastedTime": 0.040357351303100589
            },
            {
                "transactionName": "UC1_TR8_OKBUTTON",
                "rawStartTime": 1575469849613,
                "rawEndTime": 1575469850032,
                "thinkTime": 0.0,
                "wastedTime": 0.0867462158203125
            }
        ]
    },
    {
        "actionName": "Create_task",
        "steps": [
            {
                "stepId": "STEP26",
                "stepName": "Url: /api/user/catalog/node/0/children/",
                "infFile": "t32.inf",
                "time": 1575469850396
            },
            {
                "stepId": "STEP27",
                "stepName": "Url: /api/shops?q=&page=0",
                "infFile": "t34.inf",
                "time": 1575469850589
            },
            {
                "stepId": "STEP28",
                "stepName": "Custom Request: DB_Request",
                "infFile": "t35.inf",
                "time": 1575469850646
            },
            {
                "stepId": "STEP29",
                "stepName": "Url: /api/user/catalog/node/0/children/",
                "infFile": "t36.inf",
                "time": 1575469850730
            },
            {
                "stepId": "STEP30",
                "stepName": "Url: /api/user/catalog/treeview?shopid={shopid}",
                "infFile": "t39.inf",
                "time": 1575469851097
            },
            {
                "stepId": "STEP31",
                "stepName": "Custom Request: DB_Request",
                "infFile": "t40.inf",
                "time": 1575469851148
            },
            {
                "stepId": "STEP32",
                "stepName": "Url: /api/user/catalog/node/191/children/",
                "infFile": "t41.inf",
                "time": 1575469851316
            },
            {
                "stepId": "STEP33",
                "stepName": "Url: /api/user/catalog/node/191/service/",
                "infFile": "t42.inf",
                "time": 1575469851404
            },
            {
                "stepId": "STEP34",
                "stepName": "Url: /api/user/catalog/breadcrumbs/191",
                "infFile": "t43.inf",
                "time": 1575469851487
            },
            {
                "stepId": "STEP35",
                "stepName": "Url: /api/inventoryNumbers?serviceId={serviceID}&shopId={shopid}",
                "infFile": "t45.inf",
                "time": 1575469851557
            },
            {
                "stepId": "STEP36",
                "stepName": "Custom Request: DB_Request",
                "infFile": "t46.inf",
                "time": 1575469851611
            },
            {
                "stepId": "STEP37",
                "stepName": "Url: /api/inventoryNumbers?shopId={shopid}&serviceId={serviceID}&serviceId={serviceID}&q=&page=0",
                "infFile": "t47.inf",
                "time": 1575469851766
            },
            {
                "stepId": "STEP38",
                "stepName": "Custom Request: /api/ticket/",
                "infFile": "t48.inf",
                "time": 1575469851987
            }
        ],
        "transactions": [
            {
                "transactionName": "UC1_TR2_NEWINC",
                "rawStartTime": 1575469850276,
                "rawEndTime": 1575469850399,
                "thinkTime": 0.0,
                "wastedTime": 0.019156217575073243
            },
            {
                "transactionName": "UC1_TR3_LOCATION",
                "rawStartTime": 1575469850460,
                "rawEndTime": 1575469851151,
                "thinkTime": 0.0,
                "wastedTime": 0.12802600860595704
            },
            {
                "transactionName": "UC1_TR4_QUESTION",
                "rawStartTime": 1575469851231,
                "rawEndTime": 1575469851613,
                "thinkTime": 0.0,
                "wastedTime": 0.09874343872070313
            },
            {
                "transactionName": "UC1_TR5_INVNUMBER",
                "rawStartTime": 1575469851676,
                "rawEndTime": 1575469851768,
                "thinkTime": 0.0,
                "wastedTime": 0.018858909606933595
            },
            {
                "transactionName": "UC1_TR7_CREATE",
                "rawStartTime": 1575469851836,
                "rawEndTime": 1575469851988,
                "thinkTime": 0.0,
                "wastedTime": 0.02057933807373047
            }
        ]
    },
    {
        "actionName": "Comment_task",
        "steps": [
            {
                "stepId": "STEP39",
                "stepName": "Url: /api/task/countByState/",
                "infFile": "t49.inf",
                "time": 1575469852327
            },
            {
                "stepId": "STEP40",
                "stepName": "Custom Request: /api/task/?state=1&page=0&size=10",
                "infFile": "t51.inf",
                "time": 1575469853813
            },
            {
                "stepId": "STEP41",
                "stepName": "Custom Request: DB_Request",
                "infFile": "t52.inf",
                "time": 1575469853874
            },
            {
                "stepId": "STEP42",
                "stepName": "Url: /engineer/task/task.dust",
                "infFile": "t53.inf",
                "time": 1575469854081
            },
            {
                "stepId": "STEP43",
                "stepName": "Url: /engineer/task/task.js",
                "infFile": "t54.inf",
                "time": 1575469854184
            },
            {
                "stepId": "STEP44",
                "stepName": "Url: /api/task/{TaskID}",
                "infFile": "t55.inf",
                "time": 1575469855039
            },
            {
                "stepId": "STEP45",
                "stepName": "Url: /api/checkLogin",
                "infFile": "t56.inf",
                "time": 1575469855080
            },
            {
                "stepId": "STEP46",
                "stepName": "Url: /api/ticket/{TaskID}/comment/",
                "infFile": "t57.inf",
                "time": 1575469857313
            },
            {
                "stepId": "STEP47",
                "stepName": "Custom Request: /api/ticket/{TaskID}/comment/",
                "infFile": "t58.inf",
                "time": 1575469857723
            },
            {
                "stepId": "STEP48",
                "stepName": "Custom Request: DB_Request",
                "infFile": "t59.inf",
                "time": 1575469857780
            },
            {
                "stepId": "STEP49",
                "stepName": "Url: /api/ticket/{TaskID}/comment/",
                "infFile": "t60.inf",
                "time": 1575469859637
            }
        ],
        "transactions": [
            {
                "transactionName": "UC3_TR2_SELECT_TASKS",
                "rawStartTime": 1575469852186,
                "rawEndTime": 1575469853875,
                "thinkTime": 0.0,
                "wastedTime": 0.07984542846679688
            },
            {
                "transactionName": "UC3_TR3_OPEN_TASK",
                "rawStartTime": 1575469853945,
                "rawEndTime": 1575469857315,
                "thinkTime": 0.0,
                "wastedTime": 0.10608696937561035
            },
            {
                "transactionName": "UC3_TR5_SUBMIT_COMMENT",
                "rawStartTime": 1575469857394,
                "rawEndTime": 1575469859639,
                "thinkTime": 0.0,
                "wastedTime": 0.059420108795166019
            }
        ]
    },
    {
        "actionName": "Comment_task",
        "steps": [
            {
                "stepId": "STEP50",
                "stepName": "Url: /api/task/countByState/",
                "infFile": "t61.inf",
                "time": 1575469859948
            },
            {
                "stepId": "STEP51",
                "stepName": "Custom Request: /api/task/?state=1&page=0&size=10",
                "infFile": "t63.inf",
                "time": 1575469861071
            },
            {
                "stepId": "STEP52",
                "stepName": "Custom Request: DB_Request",
                "infFile": "t64.inf",
                "time": 1575469861122
            },
            {
                "stepId": "STEP53",
                "stepName": "Url: /engineer/task/task.dust",
                "infFile": "t65.inf",
                "time": 1575469861326
            },
            {
                "stepId": "STEP54",
                "stepName": "Url: /engineer/task/task.js",
                "infFile": "t66.inf",
                "time": 1575469861388
            },
            {
                "stepId": "STEP55",
                "stepName": "Url: /api/task/{TaskID}",
                "infFile": "t67.inf",
                "time": 1575469862147
            },
            {
                "stepId": "STEP56",
                "stepName": "Url: /api/checkLogin",
                "infFile": "t68.inf",
                "time": 1575469862198
            },
            {
                "stepId": "STEP57",
                "stepName": "Url: /api/ticket/{TaskID}/comment/",
                "infFile": "t69.inf",
                "time": 1575469864149
            },
            {
                "stepId": "STEP58",
                "stepName": "Custom Request: /api/ticket/{TaskID}/comment/",
                "infFile": "t70.inf",
                "time": 1575469864520
            },
            {
                "stepId": "STEP59",
                "stepName": "Custom Request: DB_Request",
                "infFile": "t71.inf",
                "time": 1575469864576
            },
            {
                "stepId": "STEP60",
                "stepName": "Url: /api/ticket/{TaskID}/comment/",
                "infFile": "t72.inf",
                "time": 1575469866558
            }
        ],
        "transactions": [
            {
                "transactionName": "UC3_TR2_SELECT_TASKS",
                "rawStartTime": 1575469859843,
                "rawEndTime": 1575469861124,
                "thinkTime": 0.0,
                "wastedTime": 0.05809426307678223
            },
            {
                "transactionName": "UC3_TR3_OPEN_TASK",
                "rawStartTime": 1575469861203,
                "rawEndTime": 1575469864151,
                "thinkTime": 0.0,
                "wastedTime": 0.10663771629333496
            },
            {
                "transactionName": "UC3_TR5_SUBMIT_COMMENT",
                "rawStartTime": 1575469864233,
                "rawEndTime": 1575469866559,
                "thinkTime": 0.0,
                "wastedTime": 0.06697893142700196
            }
        ]
    },
    {
        "actionName": "Comment_task",
        "steps": [
            {
                "stepId": "STEP61",
                "stepName": "Url: /api/task/countByState/",
                "infFile": "t73.inf",
                "time": 1575469866918
            },
            {
                "stepId": "STEP62",
                "stepName": "Custom Request: /api/task/?state=1&page=0&size=10",
                "infFile": "t75.inf",
                "time": 1575469868077
            },
            {
                "stepId": "STEP63",
                "stepName": "Custom Request: DB_Request",
                "infFile": "t76.inf",
                "time": 1575469868126
            },
            {
                "stepId": "STEP64",
                "stepName": "Url: /engineer/task/task.dust",
                "infFile": "t77.inf",
                "time": 1575469868349
            },
            {
                "stepId": "STEP65",
                "stepName": "Url: /engineer/task/task.js",
                "infFile": "t78.inf",
                "time": 1575469868454
            },
            {
                "stepId": "STEP66",
                "stepName": "Url: /api/task/{TaskID}",
                "infFile": "t79.inf",
                "time": 1575469868572
            },
            {
                "stepId": "STEP67",
                "stepName": "Url: /api/checkLogin",
                "infFile": "t80.inf",
                "time": 1575469868686
            }
        ],
        "transactions": [
            {
                "transactionName": "UC3_TR2_SELECT_TASKS",
                "rawStartTime": 1575469866768,
                "rawEndTime": 1575469868129,
                "thinkTime": 0.0,
                "wastedTime": 0.05790233612060547
            },
            {
                "transactionName": "UC3_TR3_OPEN_TASK",
                "rawStartTime": 1575469868208,
                "rawEndTime": 1575469869952,
                "thinkTime": 0.0,
                "wastedTime": 0.09817075729370117
            }
        ]
    }
]